{
  "anyrouter_dctx": {
    "quota": 563.28,
    "used": 236.72
  },
  "anyrouter_ljq": {
    "quota": 600.0,
    "used": 99.76
  },
  "anyrouter_zc": {
    "quota": 622.4,
    "used": 77.6
  },
  "anyrouter_linuxdo_84404": {
    "quota": 596.12,
    "used": 53.88
  },
  "anyrouter_linux_chuang": {
    "quota": 175.0,
    "used": 0.0
  },
  "anyrouter_linux_bwj": {
    "quota": 175.0,
    "used": 0.0
  },
  "anyrouter_linux_devbai": {
    "quota": 150.0,
    "used": 0.0
  },
  "anyrouter_linux_Yeahnet": {
    "quota": 150.0,
    "used": 0.0
  },
  "agentrouter_github_dctx479": {
    "quota": 327.6,
    "used": 467.4
  },
  "agentrouter_github_dctx-coder": {
    "quota": 286.99,
    "used": 88.01
  },
  "agentrouter_github_dctx-ARBot": {
    "quota": 203.19,
    "used": 171.81
  },
  "agentrouter_linuxdo_bwj": {
    "quota": 326.12,
    "used": 48.88
  }
}